leadbutt.py
plumbum.py
cloudwatch_to_graphite-0.11.0.dist-info/DESCRIPTION.rst
cloudwatch_to_graphite-0.11.0.dist-info/METADATA
cloudwatch_to_graphite-0.11.0.dist-info/RECORD
cloudwatch_to_graphite-0.11.0.dist-info/WHEEL
cloudwatch_to_graphite-0.11.0.dist-info/entry_points.txt
cloudwatch_to_graphite-0.11.0.dist-info/metadata.json
cloudwatch_to_graphite-0.11.0.dist-info/top_level.txt
