Metadata-Version: 2.0
Name: cloudwatch-to-graphite
Version: 0.11.0
Summary: Helper for pushing AWS CloudWatch metrics to Graphite
Home-page: https://github.com/crccheck/cloudwatch-to-graphite
Author: Chris Chang
Author-email: c@crccheck.com
License: Apache License, Version 2.0
Platform: UNKNOWN
Classifier: Development Status :: 4 - Beta
Classifier: Environment :: Web Environment
Classifier: Intended Audience :: Developers
Classifier: License :: OSI Approved :: Apache Software License
Classifier: Operating System :: OS Independent
Classifier: Programming Language :: Python :: 2
Classifier: Programming Language :: Python :: 2.7
Classifier: Programming Language :: Python :: 3
Classifier: Programming Language :: Python :: 3.4
Classifier: Programming Language :: Python :: 3.5
Classifier: Programming Language :: Python :: 3.6
Requires-Dist: boto
Requires-Dist: PyYAML
Requires-Dist: docopt
Requires-Dist: Jinja2
Requires-Dist: retrying
